fastapi_query_flatten/__init__.py
fastapi_query_flatten/middleware.py
fastapi_query_flatten-0.1.2.dist-info/LICENSE
fastapi_query_flatten-0.1.2.dist-info/METADATA
fastapi_query_flatten-0.1.2.dist-info/WHEEL
fastapi_query_flatten-0.1.2.dist-info/RECORD
