Metadata-Version: 2.1
Name: fastapi-query-flatten
Version: 0.1.2
Summary: 
Home-page: https://github.com/davidlin2k/fastapi-query-flatten
Author: David Lin
Author-email: davidzylin@outlook.com
Requires-Python: >=3.8.1
Classifier: Programming Language :: Python :: 3
Classifier: Programming Language :: Python :: 3.9
Classifier: Programming Language :: Python :: 3.10
Classifier: Programming Language :: Python :: 3.11
Classifier: Programming Language :: Python :: 3.12
Requires-Dist: fastapi (>=0.60.0)
Project-URL: Repository, https://github.com/davidlin2k/fastapi-query-flatten
